{"_type":"export","__export_format":4,"__export_date":"2019-07-19T04:37:11.312Z","__export_source":"insomnia.desktop.app:v6.4.1","resources":[{"_id":"req_a54a695986d740bbbe2f67348b30286f","authentication":{},"body":{},"created":1563341352289,"description":"","headers":[],"isPrivate":false,"metaSortKey":-1563341352289,"method":"POST","modified":1563511009232,"name":"/products","parameters":[],"parentId":"wrk_9c37ba1253a840a9bb560465454111a2","settingDisableRenderRequestBody":false,"settingEncodeUrl":true,"settingMaxTimelineDataSize":1000,"settingRebuildPath":true,"settingSendCookies":true,"settingStoreCookies":true,"url":"http://{{ domain  }}/products","_type":"request"},{"_id":"wrk_9c37ba1253a840a9bb560465454111a2","created":1563341113577,"description":"","modified":1563341113577,"name":"MVC example","parentId":null,"_type":"workspace"},{"_id":"req_57c163e8876b4ef798c2e06548e5181b","authentication":{},"body":{},"created":1563346797276,"description":"","headers":[],"isPrivate":false,"metaSortKey":-1560473662236,"method":"GET","modified":1563511004232,"name":"/products (GET)","parameters":[],"parentId":"wrk_9c37ba1253a840a9bb560465454111a2","settingDisableRenderRequestBody":false,"settingEncodeUrl":true,"settingMaxTimelineDataSize":1000,"settingRebuildPath":true,"settingSendCookies":true,"settingStoreCookies":true,"url":"http://{{ domain  }}/products","_type":"request"},{"_id":"req_603ae0c2baca41ee8df2636b5f735c2b","authentication":{},"body":{"mimeType":"application/json","text":"{\n\t\"product_ids\": [1, 2, 3]\n}"},"created":1563341399239,"description":"","headers":[{"name":"Content-Type","value":"application/json"}],"isPrivate":false,"metaSortKey":-1557605972183,"method":"POST","modified":1563510998768,"name":"/orders","parameters":[],"parentId":"wrk_9c37ba1253a840a9bb560465454111a2","settingDisableRenderRequestBody":false,"settingEncodeUrl":true,"settingMaxTimelineDataSize":1000,"settingRebuildPath":true,"settingSendCookies":true,"settingStoreCookies":true,"url":"http://{{ domain  }}/orders","_type":"request"},{"_id":"req_ff2bc5ac65ca415d82ad14a8526b9bd6","authentication":{},"body":{"mimeType":"application/json","text":"{\n    \"id\": 7,\n    \"sum\": 36.3105\n}"},"created":1563346929651,"description":"","headers":[{"name":"Content-Type","value":"application/json"}],"isPrivate":false,"metaSortKey":-1554738282130,"method":"PUT","modified":1563510993679,"name":"/orders/{id}","parameters":[],"parentId":"wrk_9c37ba1253a840a9bb560465454111a2","settingDisableRenderRequestBody":false,"settingEncodeUrl":true,"settingMaxTimelineDataSize":1000,"settingRebuildPath":true,"settingSendCookies":true,"settingStoreCookies":true,"url":"http://{{ domain  }}/orders","_type":"request"},{"_id":"env_18a37d66f6783cb0b21a21241f402c12e7ff213c","color":null,"created":1563341113627,"data":{},"isPrivate":false,"metaSortKey":1563341113627,"modified":1563341113627,"name":"Base Environment","parentId":"wrk_9c37ba1253a840a9bb560465454111a2","_type":"environment"},{"_id":"jar_18a37d66f6783cb0b21a21241f402c12e7ff213c","cookies":[],"created":1563341113629,"modified":1563341113629,"name":"Default Jar","parentId":"wrk_9c37ba1253a840a9bb560465454111a2","_type":"cookie_jar"},{"_id":"env_c4b1787f68594f4e8016880d73b1be1d","color":null,"created":1563341128771,"data":{"domain":"locahost:8080"},"isPrivate":false,"metaSortKey":1563341128771,"modified":1563510984431,"name":"dev","parentId":"env_18a37d66f6783cb0b21a21241f402c12e7ff213c","_type":"environment"}]}